chadhmm/__init__.py
chadhmm/distributions/multinomial.py
chadhmm/hmm/BaseHMM.py
chadhmm/hmm/GaussianHMM.py
chadhmm/hmm/GaussianMixtureHMM.py
chadhmm/hmm/MultinomialHMM.py
chadhmm/hmm/PoissonHMM.py
chadhmm/hmm/__init__.py
chadhmm/hsmm/BaseHSMM.py
chadhmm/hsmm/GaussianHSMM.py
chadhmm/hsmm/GaussianMixtureHSMM.py
chadhmm/hsmm/MultinomialHSMM.py
chadhmm/hsmm/PoissonHSMM.py
chadhmm/hsmm/__init__.py
chadhmm/schemas/__init__.py
chadhmm/schemas/common.py
chadhmm/schemas/data_models.py
chadhmm/utils/__init__.py
chadhmm/utils/constraints.py
chadhmm/utils/convergence_handle.py
chadhmm/utils/seed.py
chadhmm-0.4.0.dist-info/METADATA
chadhmm-0.4.0.dist-info/WHEEL
chadhmm-0.4.0.dist-info/licenses/LICENSE
chadhmm-0.4.0.dist-info/RECORD
