Metadata-Version: 2.4
Name: chadhmm
Version: 0.4.0
Summary: Package for Hidden Markov and Hidden Semi-Markov Models
Project-URL: Homepage, https://github.com/GarroshIcecream/chadhmm
Project-URL: Repository, https://github.com/GarroshIcecream/chadhmm
Project-URL: Issues, https://github.com/GarroshIcecream/chadhmm/issues
Author-email: GarroshIcecream <garroshicecream@gmail.com>
License: MIT
License-File: LICENSE
Keywords: contexthmm,contexthsmm,ghmm,ghsmm,gmm,hidden-markov-model,hidden-semi-markov-model,hmm,hsmm,parametrichmm
Classifier: Development Status :: 4 - Beta
Classifier: Intended Audience :: Developers
Classifier: License :: OSI Approved :: MIT License
Classifier: Programming Language :: Python :: 3
Classifier: Programming Language :: Python :: 3.12
Classifier: Topic :: Scientific/Engineering :: Artificial Intelligence
Classifier: Topic :: Scientific/Engineering :: Mathematics
Requires-Python: >=3.12
Requires-Dist: matplotlib>=3.7.2
Requires-Dist: numpy>=1.22.1
Requires-Dist: scikit-learn>=1.5.0
Requires-Dist: torch>=2.2.0
Provides-Extra: dev
Requires-Dist: mypy>=1.0.0; extra == 'dev'
Requires-Dist: pytest-cov>=4.0.0; extra == 'dev'
Requires-Dist: pytest>=7.0.0; extra == 'dev'
